additionOPr/__init__.py
additionOPr-0.0.1.dist-info/LICENCE.txt
additionOPr-0.0.1.dist-info/METADATA
additionOPr-0.0.1.dist-info/WHEEL
additionOPr-0.0.1.dist-info/top_level.txt
additionOPr-0.0.1.dist-info/RECORD
