Metadata-Version: 2.1
Name: additionOPr
Version: 0.0.1
Summary: This package provides a function to add two numbers
Author: Roqaiah Jamil
Author-email: roqaiahjamil96@gmail.com
Classifier: Programming Language :: Python :: 3
Classifier: License :: OSI Approved :: MIT License
Classifier: Operating System :: OS Independent
License-File: LICENCE.txt
